{
  "_metadata": {
    "description": "Stock portfolio tracking data",
    "sourceOfTruth": "This file is the single source of truth for all stock data. All changes must be persisted here before being returned to the frontend."
  },
  "search": "yahoo finance",
  "stocks": [
    {
      "symbol": "TSLA",
      "name": "TSLA",
      "price": 0.0,
      "changePercent": 0.0,
      "date": "2026-01-24T05:00:00+08:00",
      "buyPrice": 380.0,
      "diff": 0
    },
    {
      "symbol": "META",
      "name": "META",
      "price": 0.0,
      "changePercent": 0.0,
      "date": "2026-01-24T05:00:00+08:00",
      "buyPrice": 630.0,
      "diff": 0
    },
    {
      "symbol": "SNDK",
      "name": "Sandisk Corporation",
      "price": 473.83,
      "changePercent": -5.88,
      "date": "2026-01-24T05:00:00+08:00",
      "buyPrice": 600.0,
      "diff": 26.63
    },
    {
      "symbol": "AAOI",
      "name": "Applied Optoelectronics, Inc.",
      "price": 35.72,
      "changePercent": -6.37,
      "date": "2026-01-24T05:00:00+08:00",
      "buyPrice": 47.0,
      "diff": 31.58
    },
    {
      "symbol": "AAPL",
      "name": "AAPL",
      "price": 0.0,
      "changePercent": 0.0,
      "date": "2026-01-24T05:00:00+08:00",
      "buyPrice": 255.0,
      "diff": 0
    }
  ]
}